tukey/__init__.py
tukey/tukey.py
tukey-0.1.0.dist-info/LICENSE.txt
tukey-0.1.0.dist-info/METADATA
tukey-0.1.0.dist-info/WHEEL
tukey-0.1.0.dist-info/entry_points.txt
tukey-0.1.0.dist-info/top_level.txt
tukey-0.1.0.dist-info/RECORD
