Metadata-Version: 2.1
Name: tukey
Version: 0.1.0
Summary: A python based math module
Author-email: Shubhranil Basak <Shubhranil.Basak@iiitb.ac.in>
Maintainer-email: Shubhranil Basak <Shubhranil.Basak@iiitb.ac.in>
License: GNU GENERAL PUBLIC LICENSE
Project-URL: Homepage, https://github.com/Shubhranil-Basak/tukey
Project-URL: Bug Reports, https://github.com/Shubhranil-Basak/tukey/issues
Project-URL: Funding, https://donate.pypi.org
Project-URL: Source, https://github.com/Shubhranil-Basak/tukey/
Keywords: math,python,development
Classifier: Development Status :: 1 - Planning
Classifier: Intended Audience :: Education
Classifier: License :: OSI Approved :: GNU General Public License v3 (GPLv3)
Classifier: Operating System :: OS Independent
Classifier: Programming Language :: Python :: 3
Classifier: Programming Language :: Python :: 3.8
Classifier: Programming Language :: Python :: 3.9
Classifier: Programming Language :: Python :: 3.10
Classifier: Programming Language :: Python :: 3.11
Classifier: Programming Language :: Python :: 3.12
Classifier: Programming Language :: Python :: 3 :: Only
Requires-Python: >=3.8
License-File: LICENSE.txt
